LICENSE
MANIFEST.in
README.md
README.rst
pyproject.toml
setup.cfg
setup.py
jobber/jobber.py
mbox2m365/__init__.py
mbox2m365/__main__.py
mbox2m365/db_make.py
mbox2m365/mailSink.orig.py
mbox2m365/mailSink.py
mbox2m365/mailSinkAuth.py
mbox2m365/mailSinknx.py
mbox2m365/mailTLS.py
mbox2m365/mailTest.py
mbox2m365/mainSink.py
mbox2m365/mbox2m365.py
mbox2m365.egg-info/PKG-INFO
mbox2m365.egg-info/SOURCES.txt
mbox2m365.egg-info/dependency_links.txt
mbox2m365.egg-info/entry_points.txt
mbox2m365.egg-info/requires.txt
mbox2m365.egg-info/top_level.txt