Metadata-Version: 2.1
Name: mbox2m365
Version: 3.2.16
Summary: 'Send a message stored within an mbox using m365 (Office365)'
Home-page: https://github.com/FNNDSC/mbox2m365
Author: Rudolph Pienaar
Author-email: rudolph.pienaar@childrens.harvard.edu
License: MIT
License-File: LICENSE
Requires-Dist: pfmisc
Requires-Dist: pudb
Requires-Dist: appdirs
